self_messages/__init__.py
self_messages-8.1.dist-info/METADATA
self_messages-8.1.dist-info/WHEEL
self_messages-8.1.dist-info/top_level.txt
self_messages-8.1.dist-info/RECORD
