Metadata-Version: 2.1
Name: self-messages
Version: 8.1
Summary: Fix for discord self bots being nuked
Home-page: https://github.com/ylmonkey/selfmessages
Author: forbidden
Author-email: chodecode69@gmail.com
License: MIT
Platform: UNKNOWN
